{
  "presupuestos": [
    {
      "code": "123",
      "initValue": 100
    },
    {
      "code": "111",
      "initValue": 1000
    }
  ],
  "ingresos": [
    {
      "dimension": "123",
      "programa": "111",
      "fecha": "12-10-2021",
      "factura": "11",
      "proveedor": "",
      "responsable": "11",
      "ciudad": "QUITO",
      "observacion": "11",
      "empresa": "",
      "cedula": "11",
      "correo": "",
      "montoCurso": 0,
      "porcentajeBeca": 0,
      "montoBeca": 0,
      "abono": 0,
      "saldo": 0,
      "numBoucher": "",
      "numDeposito": "",
      "transferencia": "",
      "id": "f3c76d59-f826-4d4c-a2fc-cb2db487d2e2"
    }
  ],
  "gastos": []
}